Testsuite: comp207p.target.ConstantVariableFoldingTest
<<<<<<< Updated upstream
Tests run: 4, Failures: 0, Errors: 4, Skipped: 0, Time elapsed: 0.02 sec
=======
<<<<<<< Updated upstream
Tests run: 4, Failures: 0, Errors: 4, Skipped: 0, Time elapsed: 0.024 sec
=======
Tests run: 4, Failures: 0, Errors: 4, Skipped: 0, Time elapsed: 0.016 sec
>>>>>>> Stashed changes
>>>>>>> Stashed changes

Testcase: testMethodThree took 0.001 sec
	Caused an ERROR
Operand stack underflow
Exception Details:
  Location:
    comp207p/target/ConstantVariableFolding.<init>()V @0: invokespecial
  Reason:
    Attempt to pop empty stack.
  Current Frame:
    bci: @0
    flags: { flagThisUninit }
    locals: { uninitializedThis }
    stack: { }
  Bytecode:
    0x0000000: b700 01b1                              

java.lang.VerifyError: Operand stack underflow
Exception Details:
  Location:
    comp207p/target/ConstantVariableFolding.<init>()V @0: invokespecial
  Reason:
    Attempt to pop empty stack.
  Current Frame:
    bci: @0
    flags: { flagThisUninit }
    locals: { uninitializedThis }
    stack: { }
  Bytecode:
    0x0000000: b700 01b1                              

	at comp207p.target.ConstantVariableFoldingTest.<init>(Unknown Source)
	at java.lang.reflect.Constructor.newInstance(Constructor.java:422)

Testcase: testMethodFour took 0 sec
	Caused an ERROR
Operand stack underflow
Exception Details:
  Location:
    comp207p/target/ConstantVariableFolding.<init>()V @0: invokespecial
  Reason:
    Attempt to pop empty stack.
  Current Frame:
    bci: @0
    flags: { flagThisUninit }
    locals: { uninitializedThis }
    stack: { }
  Bytecode:
    0x0000000: b700 01b1                              

java.lang.VerifyError: Operand stack underflow
Exception Details:
  Location:
    comp207p/target/ConstantVariableFolding.<init>()V @0: invokespecial
  Reason:
    Attempt to pop empty stack.
  Current Frame:
    bci: @0
    flags: { flagThisUninit }
    locals: { uninitializedThis }
    stack: { }
  Bytecode:
    0x0000000: b700 01b1                              

	at comp207p.target.ConstantVariableFoldingTest.<init>(Unknown Source)
	at java.lang.reflect.Constructor.newInstance(Constructor.java:422)

Testcase: testMethodOne took 0 sec
	Caused an ERROR
Operand stack underflow
Exception Details:
  Location:
    comp207p/target/ConstantVariableFolding.<init>()V @0: invokespecial
  Reason:
    Attempt to pop empty stack.
  Current Frame:
    bci: @0
    flags: { flagThisUninit }
    locals: { uninitializedThis }
    stack: { }
  Bytecode:
    0x0000000: b700 01b1                              

java.lang.VerifyError: Operand stack underflow
Exception Details:
  Location:
    comp207p/target/ConstantVariableFolding.<init>()V @0: invokespecial
  Reason:
    Attempt to pop empty stack.
  Current Frame:
    bci: @0
    flags: { flagThisUninit }
    locals: { uninitializedThis }
    stack: { }
  Bytecode:
    0x0000000: b700 01b1                              

	at comp207p.target.ConstantVariableFoldingTest.<init>(Unknown Source)
	at java.lang.reflect.Constructor.newInstance(Constructor.java:422)

Testcase: testMethodTwo took 0 sec
	Caused an ERROR
Operand stack underflow
Exception Details:
  Location:
    comp207p/target/ConstantVariableFolding.<init>()V @0: invokespecial
  Reason:
    Attempt to pop empty stack.
  Current Frame:
    bci: @0
    flags: { flagThisUninit }
    locals: { uninitializedThis }
    stack: { }
  Bytecode:
    0x0000000: b700 01b1                              

java.lang.VerifyError: Operand stack underflow
Exception Details:
  Location:
    comp207p/target/ConstantVariableFolding.<init>()V @0: invokespecial
  Reason:
    Attempt to pop empty stack.
  Current Frame:
    bci: @0
    flags: { flagThisUninit }
    locals: { uninitializedThis }
    stack: { }
  Bytecode:
    0x0000000: b700 01b1                              

	at comp207p.target.ConstantVariableFoldingTest.<init>(Unknown Source)
	at java.lang.reflect.Constructor.newInstance(Constructor.java:422)

